setup.py
pyRuuviTracker.egg-info/PKG-INFO
pyRuuviTracker.egg-info/SOURCES.txt
pyRuuviTracker.egg-info/dependency_links.txt
pyRuuviTracker.egg-info/requires.txt
pyRuuviTracker.egg-info/top_level.txt
rt_client/__init__.py
rt_client/api_v1.py