Metadata-Version: 1.0
Name: pyRuuviTracker
Version: 0.12
Summary: Client library for RuuviTracker in Python
Home-page: https://github.com/kipe/pyRuuviTracker
Author: Kimmo Huoman
Author-email: kipenroskaposti@gmail.com
License: UNKNOWN
Platform: UNKNOWN
